{
  "request_info": {
    "success": true,
    "credits_used": 13854,
    "overage_used": 3854,
    "credits_used_this_request": 1,
    "credits_remaining": 0,
    "credits_reset_at": "2025-05-18T13:34:32.000Z"
  },
  "request_parameters": {
    "type": "product",
    "url": "https://www.homedepot.com/p/NewTechWood-Bell-Series-0-88-in-x-5-5-in-x-16-ft-Grooved-Brazilian-IPE-Composite-Decking-Board-US53-16-IP/332222367"
  },
  "request_metadata": {
    "created_at": "2025-05-01T17:03:20.119Z",
    "processed_at": "2025-05-01T17:03:28.512Z",
    "total_time_taken": 8.39,
    "homedepot_url": "https://www.homedepot.com/p/NewTechWood-Bell-Series-0-88-in-x-5-5-in-x-16-ft-Grooved-Brazilian-IPE-Composite-Decking-Board-US53-16-IP/332222367"
  },
  "product": {
    "link": "https://www.homedepot.com/p/NewTechWood-Bell-Series-0-88-in-x-5-5-in-x-16-ft-Grooved-Brazilian-IPE-Composite-Decking-Board-US53-16-IP/332222367",
    "brand": "NewTechWood",
    "brand_link": "https://www.homedepot.com/b/Lumber-Composites-Decking-Deck-Boards-Composite-Decking-Boards/NewTechWood/N-5yc1vZc5mbZbzg",
    "title": "NewTechWood Bell Series 0.88 in. x 5.5 in. x 16 ft. Grooved Brazilian IPE Composite Decking Board",
    "upc": "810146111733",
    "item_id": "332222367",
    "parent_id": "334560728",
    "store_sku": "1012823361",
    "model_number": "US53-16-IP",
    "description": "Introducing the Bell Series Decking-where timeless design meets modern durability. Capped on all 4-sides and featuring our beloved Heritage wood grain, this decking offers classic appeal with enhanced protection. Available in standard colors, it seamlessly integrates with our Cortes and Magellan series, showcasing multichromatic coloring throughout. Plus, the capped underside ensures a polished look even when the deck is visible from below.",
    "feature_bullets": [
      "Premium Wood Look without the Maintenace\u2002\u2002\u2002",
      "Capped all the way around to withstand the weather",
      "Talk to a live NewTechWood expert at 855-592-8088"
    ],
    "feature_bullets_count": 3,
    "descriptive_attributes": [
      "Heritage wood grain: classic design that adds timeless appeal to any outdoor space",
      "All-sides capped: enhanced protection against moisture, UV rays, and weather for lasting durability",
      "Multichromatic coloring: rich, dynamic hues throughout the board for a sophisticated look",
      "Standard color options: complements our cortes and magellan series for versatile design possibilities",
      "Capped underside: maintains a finished appearance even when the deck's underside is visible",
      "Seamless integration: works effortlessly with existing NewTechWood products for a cohesive outdoor aesthetic"
    ],
    "descriptive_attributes_count": 6,
    "images": [
      {
        "link": "https://images.thdstatic.com/productImages/d658232f-ed73-43e9-b843-128ecdd85592/svn/brazillian-ipe-newtechwood-composite-decking-boards-us53-16-ip-64_1000.jpg",
        "type": "primary"
      },
      {
        "link": "https://images.thdstatic.com/productImages/a6ce239e-9d24-4260-b7a4-19486937536a/svn/brazillian-ipe-newtechwood-composite-decking-boards-us53-16-ip-e1_1000.jpg",
        "type": "image_left_view"
      },
      {
        "link": "https://images.thdstatic.com/productImages/e56f493d-386e-4ea7-8622-a62613050ebd/svn/brazillian-ipe-newtechwood-composite-decking-boards-us53-16-ip-c3_1000.jpg",
        "type": "image_alternate_view"
      },
      {
        "link": "https://images.thdstatic.com/productImages/5c270314-4edf-4a34-88f8-4e7e04ccc8a5/svn/brazillian-ipe-newtechwood-composite-decking-boards-us53-16-ip-4f_1000.jpg",
        "type": "image_alternate_view_2"
      },
      {
        "link": "https://images.thdstatic.com/productImages/5b319012-979b-4f86-b84e-6a2b24b542d3/svn/brazillian-ipe-newtechwood-composite-decking-boards-us53-16-ip-fa_1000.jpg",
        "type": "image_alternate_view_5"
      },
      {
        "link": "https://images.thdstatic.com/productImages/690c53c8-cc21-49e7-bf1d-5f293f66f850/svn/brazillian-ipe-newtechwood-composite-decking-boards-us53-16-ip-76_1000.jpg",
        "type": "image_alternate_view_6"
      }
    ],
    "main_image": {
      "link": "https://images.thdstatic.com/productImages/d658232f-ed73-43e9-b843-128ecdd85592/svn/brazillian-ipe-newtechwood-composite-decking-boards-us53-16-ip-64_1000.jpg",
      "type": "primary"
    },
    "ratings_total": 0,
    "specifications": [
      {
        "group_name": "Details",
        "name": "Color Family",
        "value": "Brown"
      },
      {
        "group_name": "Details",
        "name": "Color/Finish",
        "value": "Brazillian IPE"
      },
      {
        "group_name": "Details",
        "name": "Edge Type",
        "value": "Grooved"
      },
      {
        "group_name": "Details",
        "name": "Fastener recommendation",
        "value": "NewTechWood Fasteners"
      },
      {
        "group_name": "Details",
        "name": "Features",
        "value": "Hidden Fasteners Compatibility,UV Protected,Water Resistant"
      },
      {
        "group_name": "Details",
        "name": "Material",
        "value": "Composite"
      },
      {
        "group_name": "Details",
        "name": "Returnable",
        "value": "90-Day"
      },
      {
        "group_name": "Details",
        "name": "Total Linear Feet Covered",
        "value": "16"
      },
      {
        "group_name": "Warranty / Certifications",
        "name": "Manufacturer Warranty",
        "value": "25 Years"
      },
      {
        "group_name": "Dimensions",
        "name": "Actual Product Length (ft.)",
        "value": "16 ft"
      },
      {
        "group_name": "Dimensions",
        "name": "Actual Product Thickness (in.)",
        "value": "0.88 in"
      },
      {
        "group_name": "Dimensions",
        "name": "Actual Product Width (in.)",
        "value": "5.5 in"
      },
      {
        "group_name": "Dimensions",
        "name": "Approximate Weight (lb)",
        "value": "36"
      },
      {
        "group_name": "Dimensions",
        "name": "Nominal Product Length (ft.)",
        "value": "16 ft"
      },
      {
        "group_name": "Dimensions",
        "name": "Nominal Product Thickness (in.)",
        "value": "1"
      },
      {
        "group_name": "Dimensions",
        "name": "Nominal Product Width (in.)",
        "value": "5.5 in"
      }
    ],
    "variants": [
      {
        "title": "Brazillian IPE~~Grooved~~16 ft",
        "link": "https://www.homedepot.com/p/NewTechWood-Bell-Series-0-88-in-x-5-5-in-x-16-ft-Grooved-Brazilian-IPE-Composite-Decking-Board-US53-16-IP/332222367",
        "item_id": "332222367"
      },
      {
        "title": "Peruvian Teak~~Grooved~~16 ft",
        "link": "https://www.homedepot.com/p/NewTechWood-Bell-Series-0-88-in-x-5-5-in-x-16-ft-Grooved-Peruvian-Teak-Composite-Decking-Board-US53-16-TK/332222687",
        "item_id": "332222687"
      },
      {
        "title": "Indian Ebony~~Grooved~~16 ft",
        "link": "https://www.homedepot.com/p/NewTechWood-Bell-Series-0-88-in-x-5-5-in-x-16-ft-Grooved-Indian-Ebony-Composite-Decking-Board-US53-16-EB/332222057",
        "item_id": "332222057"
      },
      {
        "title": "Argentinian Silver Gray~~Grooved~~16 ft",
        "link": "https://www.homedepot.com/p/NewTechWood-Bell-Series-0-88-in-x-5-5-in-x-16-ft-Grooved-Argentinian-Silver-Gray-Composite-Decking-Board-US53-16-SI/332222616",
        "item_id": "332222616"
      },
      {
        "title": "Argentinian Silver Gray~~Grooved~~8 ft",
        "link": "https://www.homedepot.com/p/NewTechWood-Bell-Series-0-88-in-x-5-5-in-x-8-ft-Grooved-Argentinian-Silver-Gray-Composite-Decking-Board-US53-8-SI/332222907",
        "item_id": "332222907"
      },
      {
        "title": "Spanish Walnut~~Grooved~~8 ft",
        "link": "https://www.homedepot.com/p/NewTechWood-Bell-Series-0-88-in-x-5-5-in-x-8-ft-Grooved-Spanish-Walnut-Composite-Decking-Board-US53-8-WN/332222971",
        "item_id": "332222971"
      },
      {
        "title": "Roman Antique~~Grooved~~8 ft",
        "link": "https://www.homedepot.com/p/NewTechWood-Bell-Series-0-88-in-x-5-5-in-x-8-ft-Grooved-Roman-Antique-Composite-Decking-Board-US53-8-AT/332222827",
        "item_id": "332222827"
      },
      {
        "title": "Indian Ebony~~Grooved~~8 ft",
        "link": "https://www.homedepot.com/p/NewTechWood-Bell-Series-0-88-in-x-5-5-in-x-8-ft-Grooved-Indian-Ebony-Composite-Decking-Board-US53-8-EB/332222853",
        "item_id": "332222853"
      },
      {
        "title": "Peruvian Teak~~Grooved~~8 ft",
        "link": "https://www.homedepot.com/p/NewTechWood-Bell-Series-0-88-in-x-5-5-in-x-8-ft-Grooved-Peruvian-Teak-Composite-Decking-Board-US53-8-TK/332222949",
        "item_id": "332222949"
      },
      {
        "title": "Spanish Walnut~~Grooved~~16 ft",
        "link": "https://www.homedepot.com/p/NewTechWood-Bell-Series-0-88-in-x-5-5-in-x-16-ft-Grooved-Spanish-Walnut-Composite-Decking-Board-US53-16-WN/332222788",
        "item_id": "332222788"
      },
      {
        "title": "Roman Antique~~Grooved~~16 ft",
        "link": "https://www.homedepot.com/p/NewTechWood-Bell-Series-0-88-in-x-5-5-in-x-16-ft-Grooved-Roman-Antique-Composite-Decking-Board-US53-16-AT/332222004",
        "item_id": "332222004"
      },
      {
        "title": "Brazillian IPE~~Grooved~~8 ft",
        "link": "https://www.homedepot.com/p/NewTechWood-Bell-Series-0-88-in-x-5-5-in-x-8-ft-Grooved-Brazilian-IPE-Composite-Decking-Board-US53-8-IP/332222871",
        "item_id": "332222871"
      }
    ],
    "breadcrumbs": [
      {
        "name": "Lumber & Composites",
        "link": "https://www.homedepot.com/b/Lumber-Composites/N-5yc1vZbqpg"
      },
      {
        "name": "Decking",
        "link": "https://www.homedepot.com/b/Lumber-Composites-Decking/N-5yc1vZbqmg"
      },
      {
        "name": "Deck Boards",
        "link": "https://www.homedepot.com/b/Lumber-Composites-Decking-Deck-Boards/N-5yc1vZc5mh"
      },
      {
        "name": "Composite Decking Boards",
        "link": "https://www.homedepot.com/b/Lumber-Composites-Decking-Deck-Boards-Composite-Decking-Boards/N-5yc1vZc5mb"
      }
    ],
    "buybox_winner": {
      "price": 61.25,
      "currency_symbol": "$",
      "currency": "USD",
      "unit": "piece",
      "fulfillment": {
        "pickup": false,
        "ship_to_store": true,
        "ship_to_home": false,
        "scheduled_delivery": false,
        "ship_to_store_info": {
          "store_id": "0121",
          "store_state": "Cumberland",
          "store_name": "GA",
          "in_stock": true,
          "stock_level": 646,
          "price": 0,
          "start_date": "2025-05-09",
          "end_date": "2025-05-14"
        }
      }
    }
  }
}