{
  "request_info": {
    "success": true,
    "credits_used": 14778,
    "overage_used": 4778,
    "credits_used_this_request": 1,
    "credits_remaining": 0,
    "credits_reset_at": "2025-05-18T13:34:32.000Z"
  },
  "request_parameters": {
    "type": "product",
    "url": "https://www.homedepot.com/p/VEVOR-Post-Base-4-in-x-4-in-Internal-3-6-in-x-3-6-in-Heavy-Duty-Powder-Coated-Decking-Board-Steel-Post-Bracket-2-Pieces-QBLZDZTG2J447P4OSV0/329440594"
  },
  "request_metadata": {
    "created_at": "2025-05-01T19:23:00.731Z",
    "processed_at": "2025-05-01T19:23:35.999Z",
    "total_time_taken": 35.27,
    "homedepot_url": "https://www.homedepot.com/p/VEVOR-Post-Base-4-in-x-4-in-Internal-3-6-in-x-3-6-in-Heavy-Duty-Powder-Coated-Decking-Board-Steel-Post-Bracket-2-Pieces-QBLZDZTG2J447P4OSV0/329440594"
  },
  "product": {
    "link": "https://www.homedepot.com/p/VEVOR-Post-Base-4-in-x-4-in-Internal-3-6-in-x-3-6-in-Heavy-Duty-Powder-Coated-Decking-Board-Steel-Post-Bracket-2-Pieces-QBLZDZTG2J447P4OSV0/329440594",
    "brand": "VEVOR",
    "brand_link": "https://www.homedepot.com/b/Building-Materials-Building-Hardware-Post-Brackets-Post-Bases/VEVOR/N-5yc1vZc8hsZuc5",
    "title": "VEVOR Post Base 4 in. x 4 in. Internal 3.6 in. x 3.6 in. Heavy-Duty Powder-Coated Decking Board Steel Post Bracket (2-Pieces)",
    "upc": "197988458173",
    "item_id": "329440594",
    "store_sku": "1011212409",
    "model_number": "QBLZDZTG2J447P4OSV0",
    "description": "Elevating Safety and Style in Every Step. Made from sturdy carbon steel, these connectors are durable and rust-resistant. They offer stable support and can be easily installed on both concrete and wooden floors, making them versatile for fixed installations in structures like pergolas and porch railings.",
    "feature_bullets": [
      "Complete set of accessories: installation is straightforward",
      "A spray coating: corrosion resistance and rust prevention",
      "A full wrap structure design: secure and effective support"
    ],
    "feature_bullets_count": 3,
    "descriptive_attributes": [
      "Sturdy support: each individual post base measures 3.8 in. L x 5.5 in. W x6.4 in. H / 96x140x163mm, with a quantity of 2-pieces, the inner dimensions of the column base are 3.6 in. x 3.6 in. recommended for use with 3.5 in. x 3.5 in. columns, these connectors feature a full wrap structure design, providing secure and effective support without wobbling",
      "Robust and durable: the base of the connectors is made from carbon steel material with a wall thickness of 0.08 in./ 2mm, ensuring durability and resistance to deformation, they are coated with a spray coating for corrosion resistance and rust prevention, ensuring a long lifespan",
      "Easy installation: you can quickly install them following the user manual, using a drill for making holes, the product comes with screw holes for convenient and time-saving installatio",
      "Complete set of accessories: the kit includes a complete set of accessories: dovetail screws M525 (18-pieces), thin wrench M8 open-end 14 (-piece), serrated sleeves M8 (9-pieces), self-tapping screws M860 (9-pieces), installation is straightforward and hassle-free",
      "Wide range of uses: the versatile screws are suitable for both concrete and wooden floor installations, making them ideal for use in pergolas, porch railings, columns and other structures where they provide secure support",
      "Specifications: model: QBLZ-4 in.-2, main material: carbon steel, quantity: 2-pieces, net weight: 4.7 lbs./2.15 kg, product dimensions (per piece): 3.8 in. L x 5.5 in. W x 6.4 in. H es / 96 mm x 140 mm x 163 mm",
      "Package content: post bases x 2, phillips screws x 18, thin wrench x 1, serrated socket x 9, self-tapping screws x 9"
    ],
    "descriptive_attributes_count": 7,
    "images": [
      {
        "link": "https://images.thdstatic.com/productImages/4d4439de-a0e2-5245-b643-d88c9022ad8e/svn/vevor-post-bases-qblzdztg2j447p4osv0-64_1000.jpg",
        "type": "primary"
      },
      {
        "link": "https://images.thdstatic.com/productImages/c94a9986-361f-5ddf-8c50-1b5c80585c00/svn/vevor-post-bases-qblzdztg2j447p4osv0-c3_1000.jpg",
        "type": "image_alternate_view"
      },
      {
        "link": "https://images.thdstatic.com/productImages/3c72e933-b9d8-5261-b213-a172f541cb6d/svn/vevor-post-bases-qblzdztg2j447p4osv0-4f_1000.jpg",
        "type": "image_alternate_view_2"
      },
      {
        "link": "https://images.thdstatic.com/productImages/cda3e17e-1c44-5ec3-83a3-8ff9c2c1e196/svn/vevor-post-bases-qblzdztg2j447p4osv0-1f_1000.jpg",
        "type": "image_alternate_view_3"
      },
      {
        "link": "https://images.thdstatic.com/productImages/54862396-5ec2-51c2-8411-47d2ddf2b7a8/svn/vevor-post-bases-qblzdztg2j447p4osv0-44_1000.jpg",
        "type": "image_alternate_view_4"
      },
      {
        "link": "https://images.thdstatic.com/productImages/67305259-a8e1-5060-a33f-16b8adc9df88/svn/vevor-post-bases-qblzdztg2j447p4osv0-fa_1000.jpg",
        "type": "image_alternate_view_5"
      },
      {
        "link": "https://images.thdstatic.com/productImages/6af7c6cd-3867-5874-bdc5-e4eb3a697a92/svn/vevor-post-bases-qblzdztg2j447p4osv0-76_1000.jpg",
        "type": "image_alternate_view_6"
      },
      {
        "link": "https://images.thdstatic.com/productImages/4f35fad2-6bdd-5226-84af-72730b79ee18/svn/vevor-post-bases-qblzdztg2j447p4osv0-31_1000.jpg",
        "type": "image_life_style"
      }
    ],
    "main_image": {
      "link": "https://images.thdstatic.com/productImages/4d4439de-a0e2-5245-b643-d88c9022ad8e/svn/vevor-post-bases-qblzdztg2j447p4osv0-64_1000.jpg",
      "type": "primary"
    },
    "ratings_total": 11,
    "rating": 4.6,
    "specifications": [
      {
        "group_name": "Details",
        "name": "Base Type",
        "value": "Regular Post Base"
      },
      {
        "group_name": "Details",
        "name": "Connector Finish",
        "value": "Powder coated"
      },
      {
        "group_name": "Details",
        "name": "Fasteners Included",
        "value": "Fasteners Included"
      },
      {
        "group_name": "Details",
        "name": "Features",
        "value": "No Additional Features"
      },
      {
        "group_name": "Details",
        "name": "Gauge",
        "value": "4"
      },
      {
        "group_name": "Details",
        "name": "Material",
        "value": "Steel"
      },
      {
        "group_name": "Details",
        "name": "Material Connector Compatibility",
        "value": "Wood to Concrete"
      },
      {
        "group_name": "Details",
        "name": "Number of Pieces",
        "value": "2"
      },
      {
        "group_name": "Details",
        "name": "Package Quantity",
        "value": "1"
      },
      {
        "group_name": "Details",
        "name": "Product Weight (lb.)",
        "value": "4.7 lb"
      },
      {
        "group_name": "Details",
        "name": "Returnable",
        "value": "90-Day"
      },
      {
        "group_name": "Warranty / Certifications",
        "name": "Manufacturer Warranty",
        "value": "1-Year"
      },
      {
        "group_name": "Dimensions",
        "name": "Nominal Post Size (in.)",
        "value": "4x4"
      },
      {
        "group_name": "Dimensions",
        "name": "Product Depth (in.)",
        "value": "6.4 in"
      },
      {
        "group_name": "Dimensions",
        "name": "Product Height (in.)",
        "value": "5.5 in"
      },
      {
        "group_name": "Dimensions",
        "name": "Product Width (in.)",
        "value": "3.8 in"
      }
    ],
    "breadcrumbs": [
      {
        "name": "Building Materials",
        "link": "https://www.homedepot.com/b/Building-Materials/N-5yc1vZaqns"
      },
      {
        "name": "Building Hardware",
        "link": "https://www.homedepot.com/b/Building-Materials-Building-Hardware/N-5yc1vZaqzs"
      },
      {
        "name": "Post Brackets",
        "link": "https://www.homedepot.com/b/Building-Materials-Building-Hardware-Post-Brackets/N-5yc1vZc8hv"
      },
      {
        "name": "Post Bases",
        "link": "https://www.homedepot.com/b/Building-Materials-Building-Hardware-Post-Brackets-Post-Bases/N-5yc1vZc8hs"
      }
    ],
    "buybox_winner": {
      "price": 17.15,
      "currency_symbol": "$",
      "currency": "USD",
      "was_price": 22.99,
      "unit": "box"
    }
  }
}